{"type": "FeatureCollection", "features": [{"type": "Feature", "properties": {"green": 1}, "geometry": {"type": "Point", "coordinates": [-71.0725, 42.3491]}}, {"type": "Feature", "properties": {"green": 1}, "geometry": {"type": "Point", "coordinates": [-71.0685, 42.3491]}}, {"type": "Feature", "properties": {"green": 1}, "geometry": {"type": "Point", "coordinates": [-71.0645, 42.3491]}}, {"type": "Feature", "properties": {"green": 1}, "geometry": {"type": "Point", "coordinates": [-71.06049999999999, 42.3491]}}, {"type": "Feature", "properties": {"green": 1}, "geometry": {"type": "Point", "coordinates": [-71.05649999999999, 42.3491]}}, {"type": "Feature", "properties": {"green": 1}, "geometry": {"type": "Point", "coordinates": [-71.05249999999998, 42.3491]}}, {"type": "Feature", "properties": {"green": 1}, "geometry": {"type": "Point", "coordinates": [-71.0725, 42.3516]}}, {"type": "Feature", "properties": {"green": 1}, "geometry": {"type": "Point", "coordinates": [-71.0685, 42.3516]}}, {"type": "Feature", "properties": {"green": 1}, "geometry": {"type": "Point", "coordinates": [-71.0645, 42.3516]}}, {"type": "Feature", "properties": {"green": 1}, "geometry": {"type": "Point", "coordinates": [-71.06049999999999, 42.3516]}}, {"type": "Feature", "properties": {"green": 1}, "geometry": {"type": "Point", "coordinates": [-71.05649999999999, 42.3516]}}, {"type": "Feature", "properties": {"green": 1}, "geometry": {"type": "Point", "coordinates": [-71.05249999999998, 42.3516]}}, {"type": "Feature", "properties": {"green": 1}, "geometry": {"type": "Point", "coordinates": [-71.0725, 42.354099999999995]}}, {"type": "Feature", "properties": {"green": 1}, "geometry": {"type": "Point", "coordinates": [-71.0685, 42.354099999999995]}}, {"type": "Feature", "properties": {"green": 1}, "geometry": {"type": "Point", "coordinates": [-71.0645, 42.354099999999995]}}, {"type": "Feature", "properties": {"green": 1}, "geometry": {"type": "Point", "coordinates": [-71.06049999999999, 42.354099999999995]}}, {"type": "Feature", "properties": {"green": 1}, "geometry": {"type": "Point", "coordinates": [-71.05649999999999, 42.354099999999995]}}, {"type": "Feature", "properties": {"green": 1}, "geometry": {"type": "Point", "coordinates": [-71.05249999999998, 42.354099999999995]}}, {"type": "Feature", "properties": {"green": 1}, "geometry": {"type": "Point", "coordinates": [-71.0725, 42.35659999999999]}}, {"type": "Feature", "properties": {"green": 1}, "geometry": {"type": "Point", "coordinates": [-71.0685, 42.35659999999999]}}, {"type": "Feature", "properties": {"green": 1}, "geometry": {"type": "Point", "coordinates": [-71.0645, 42.35659999999999]}}, {"type": "Feature", "properties": {"green": 1}, "geometry": {"type": "Point", "coordinates": [-71.06049999999999, 42.35659999999999]}}, {"type": "Feature", "properties": {"green": 1}, "geometry": {"type": "Point", "coordinates": [-71.05649999999999, 42.35659999999999]}}, {"type": "Feature", "properties": {"green": 1}, "geometry": {"type": "Point", "coordinates": [-71.05249999999998, 42.35659999999999]}}, {"type": "Feature", "properties": {"green": 1}, "geometry": {"type": "Point", "coordinates": [-71.0725, 42.35909999999999]}}, {"type": "Feature", "properties": {"green": 1}, "geometry": {"type": "Point", "coordinates": [-71.0685, 42.35909999999999]}}, {"type": "Feature", "properties": {"green": 1}, "geometry": {"type": "Point", "coordinates": [-71.0645, 42.35909999999999]}}, {"type": "Feature", "properties": {"green": 1}, "geometry": {"type": "Point", "coordinates": [-71.06049999999999, 42.35909999999999]}}, {"type": "Feature", "properties": {"green": 1}, "geometry": {"type": "Point", "coordinates": [-71.05649999999999, 42.35909999999999]}}, {"type": "Feature", "properties": {"green": 1}, "geometry": {"type": "Point", "coordinates": [-71.05249999999998, 42.35909999999999]}}, {"type": "Feature", "properties": {"green": 1}, "geometry": {"type": "Point", "coordinates": [-71.0725, 42.36159999999999]}}, {"type": "Feature", "properties": {"green": 1}, "geometry": {"type": "Point", "coordinates": [-71.0685, 42.36159999999999]}}, {"type": "Feature", "properties": {"green": 1}, "geometry": {"type": "Point", "coordinates": [-71.0645, 42.36159999999999]}}, {"type": "Feature", "properties": {"green": 1}, "geometry": {"type": "Point", "coordinates": [-71.06049999999999, 42.36159999999999]}}, {"type": "Feature", "properties": {"green": 1}, "geometry": {"type": "Point", "coordinates": [-71.05649999999999, 42.36159999999999]}}, {"type": "Feature", "properties": {"green": 1}, "geometry": {"type": "Point", "coordinates": [-71.05249999999998, 42.36159999999999]}}, {"type": "Feature", "properties": {"green": 1}, "geometry": {"type": "Point", "coordinates": [-71.0725, 42.364099999999986]}}, {"type": "Feature", "properties": {"green": 1}, "geometry": {"type": "Point", "coordinates": [-71.0685, 42.364099999999986]}}, {"type": "Feature", "properties": {"green": 1}, "geometry": {"type": "Point", "coordinates": [-71.0645, 42.364099999999986]}}, {"type": "Feature", "properties": {"green": 1}, "geometry": {"type": "Point", "coordinates": [-71.06049999999999, 42.364099999999986]}}, {"type": "Feature", "properties": {"green": 1}, "geometry": {"type": "Point", "coordinates": [-71.05649999999999, 42.364099999999986]}}, {"type": "Feature", "properties": {"green": 1}, "geometry": {"type": "Point", "coordinates": [-71.05249999999998, 42.364099999999986]}}, {"type": "Feature", "properties": {"green": 1}, "geometry": {"type": "Point", "coordinates": [-71.0725, 42.366599999999984]}}, {"type": "Feature", "properties": {"green": 1}, "geometry": {"type": "Point", "coordinates": [-71.0685, 42.366599999999984]}}, {"type": "Feature", "properties": {"green": 1}, "geometry": {"type": "Point", "coordinates": [-71.0645, 42.366599999999984]}}, {"type": "Feature", "properties": {"green": 1}, "geometry": {"type": "Point", "coordinates": [-71.06049999999999, 42.366599999999984]}}, {"type": "Feature", "properties": {"green": 1}, "geometry": {"type": "Point", "coordinates": [-71.05649999999999, 42.366599999999984]}}, {"type": "Feature", "properties": {"green": 1}, "geometry": {"type": "Point", "coordinates": [-71.05249999999998, 42.366599999999984]}}]}